wed/__init__.py
wed/database.py
wed/network.py
wed/path.py
wed/settings.json
wed/settings.py
wed/utils.py
pywed-0.0.6.dist-info/LICENSE
pywed-0.0.6.dist-info/METADATA
pywed-0.0.6.dist-info/WHEEL
pywed-0.0.6.dist-info/top_level.txt
pywed-0.0.6.dist-info/RECORD
