Metadata-Version: 2.1
Name: pywed
Version: 0.0.6
Summary: PYthon client to d-ice WEthear Database
Home-page: https://d-ice.gitlab.host/common/python/pywed
Author: Guillaume Vincke
Author-email: guillaume.vincke@dice-engineering.com
License: UNKNOWN
Platform: UNKNOWN
Classifier: Programming Language :: Python :: 3
Classifier: Operating System :: OS Independent
Requires-Dist: attrs (==19.1.0)
Requires-Dist: boto3 (==1.9.159)
Requires-Dist: botocore (==1.12.159)
Requires-Dist: cffi (==1.12.3)
Requires-Dist: cfgrib (==0.9.7)
Requires-Dist: Click (==7.0)
Requires-Dist: docutils (==0.14)
Requires-Dist: jmespath (==0.9.4)
Requires-Dist: numpy (==1.16.4)
Requires-Dist: pandas (==0.24.2)
Requires-Dist: pycparser (==2.19)
Requires-Dist: python-dateutil (==2.8.0)
Requires-Dist: pytz (==2019.1)
Requires-Dist: s3transfer (==0.2.0)
Requires-Dist: scipy (==1.3.0)
Requires-Dist: six (==1.12.0)
Requires-Dist: urllib3 (==1.25.3)
Requires-Dist: xarray (==0.12.1)
